CHANGES.txt
LICENSE.GPL
LICENSE.txt
README.txt
TODO.txt
setup.py
collective/__init__.py
collective.arboreal.egg-info/PKG-INFO
collective.arboreal.egg-info/SOURCES.txt
collective.arboreal.egg-info/dependency_links.txt
collective.arboreal.egg-info/entry_points.txt
collective.arboreal.egg-info/namespace_packages.txt
collective.arboreal.egg-info/not-zip-safe
collective.arboreal.egg-info/requires.txt
collective.arboreal.egg-info/top_level.txt
collective/arboreal/__init__.py
collective/arboreal/arboreal.gif
collective/arboreal/arboreal.py
collective/arboreal/arborealselection.py
collective/arboreal/config.py
collective/arboreal/configure.zcml
collective/arboreal/field.py
collective/arboreal/index.py
collective/arboreal/node.py
collective/arboreal/public.py
collective/arboreal/treemanager.py
collective/arboreal/utils.py
collective/arboreal/widgets.py
collective/arboreal/i18n/collective.arboreal-nl.po
collective/arboreal/profiles/default/controlpanel.xml
collective/arboreal/profiles/default/cssregistry.xml
collective/arboreal/profiles/default/jsregistry.xml
collective/arboreal/profiles/default/metadata.xml
collective/arboreal/profiles/default/propertiestool.xml
collective/arboreal/profiles/default/skins.xml
collective/arboreal/profiles/default/toolset.xml
collective/arboreal/skins/collective.arboreal/abr_add_node.cpy
collective/arboreal/skins/collective.arboreal/abr_add_node.cpy.metadata
collective/arboreal/skins/collective.arboreal/abr_add_tree.cpy
collective/arboreal/skins/collective.arboreal/abr_add_tree.cpy.metadata
collective/arboreal/skins/collective.arboreal/abr_change_node.cpy
collective/arboreal/skins/collective.arboreal/abr_change_node.cpy.metadata
collective/arboreal/skins/collective.arboreal/abr_delete_node.cpy
collective/arboreal/skins/collective.arboreal/abr_delete_node.cpy.metadata
collective/arboreal/skins/collective.arboreal/abr_delete_tree.cpy
collective/arboreal/skins/collective.arboreal/abr_delete_tree.cpy.metadata
collective/arboreal/skins/collective.arboreal/abr_get_path_segments.py
collective/arboreal/skins/collective.arboreal/abr_move_node_down.cpy
collective/arboreal/skins/collective.arboreal/abr_move_node_down.cpy.metadata
collective/arboreal/skins/collective.arboreal/abr_move_node_up.cpy
collective/arboreal/skins/collective.arboreal/abr_move_node_up.cpy.metadata
