Metadata-Version: 1.0
Name: collective.arboreal
Version: 2.0
Summary: Arboreal is a tool which lets you manage multiple trees.
Home-page: http://pypi.python.org/pypi/collective.arboreal
Author: Pareto
Author-email: info@pareto.nl
License: GPL
Keywords: archetypes trees field widget index
Platform: UNKNOWN
Classifier: Framework :: Plone
Classifier: Intended Audience :: Developers
Classifier: License :: OSI Approved :: GNU General Public License (GPL)
Classifier: Programming Language :: Python
